<?xml version="1.0"?>

<model-hints>
	<model name="com.training.mysb.model.Employee">
		<field name="empId" type="long" />
		<field name="name" type="String" />
		<field name="mobile" type="String" />
		<field name="address" type="String" />
		<field name="jobTitle" type="String" />
		<field name="groupId" type="long" />
		<field name="userId" type="long" />
		<field name="userName" type="String" />
		<field name="createDate" type="Date" />
		<field name="modifiedDate" type="Date" />
	</model>
</model-hints>